CHANGES.txt
CURRENT_VERSION
MANIFEST.in
README.txt
development.ini
production.ini
pytest.ini
requirements.txt
setup.py
autonomie_oidc_provider/__init__.py
autonomie_oidc_provider/config.py
autonomie_oidc_provider/exceptions.py
autonomie_oidc_provider/generators.py
autonomie_oidc_provider/layout.py
autonomie_oidc_provider/models.py
autonomie_oidc_provider/routes.py
autonomie_oidc_provider/scope_consumer.py
autonomie_oidc_provider/security.py
autonomie_oidc_provider/subscribers.py
autonomie_oidc_provider/template_api.py
autonomie_oidc_provider/util.py
autonomie_oidc_provider.egg-info/PKG-INFO
autonomie_oidc_provider.egg-info/SOURCES.txt
autonomie_oidc_provider.egg-info/dependency_links.txt
autonomie_oidc_provider.egg-info/entry_points.txt
autonomie_oidc_provider.egg-info/not-zip-safe
autonomie_oidc_provider.egg-info/requires.txt
autonomie_oidc_provider.egg-info/top_level.txt
autonomie_oidc_provider/plugin/__init__.py
autonomie_oidc_provider/plugin/security.py
autonomie_oidc_provider/plugin/views/__init__.py
autonomie_oidc_provider/plugin/views/client.py
autonomie_oidc_provider/plugin/views/forms.py
autonomie_oidc_provider/scripts/__init__.py
autonomie_oidc_provider/scripts/manager.py
autonomie_oidc_provider/templates/form_layout.pt
autonomie_oidc_provider/templates/logout.mako
autonomie_oidc_provider/templates/plugin/client.mako
autonomie_oidc_provider/tests/__init__.py
autonomie_oidc_provider/tests/conftest.py
autonomie_oidc_provider/tests/test_scope_consumer.py
autonomie_oidc_provider/tests/test_util.py
autonomie_oidc_provider/tests/views/__init__.py
autonomie_oidc_provider/tests/views/test_authorize.py
autonomie_oidc_provider/tests/views/test_logout.py
autonomie_oidc_provider/tests/views/test_token.py
autonomie_oidc_provider/tests/views/test_userinfo.py
autonomie_oidc_provider/views/__init__.py
autonomie_oidc_provider/views/authorize.py
autonomie_oidc_provider/views/index.py
autonomie_oidc_provider/views/login.py
autonomie_oidc_provider/views/logout.py
autonomie_oidc_provider/views/token.py
autonomie_oidc_provider/views/userinfo.py