Metadata-Version: 2.1
Name: autonomie-oidc-provider
Version: 4.2.1
Summary: autonomie_oidc_provider
Home-page: UNKNOWN
Author: 
Author-email: 
License: UNKNOWN
Keywords: web wsgi bfg pylons pyramid
Platform: UNKNOWN
Classifier: Programming Language :: Python
Classifier: Framework :: Pyramid
Classifier: Topic :: Internet :: WWW/HTTP
Classifier: Topic :: Internet :: WWW/HTTP :: WSGI :: Application
Provides-Extra: testing
Provides-Extra: dev
